digSocialMediaIdExtractor
