Metadata-Version: 1.1
Name: digSocialMediaIdExtractor
Version: 0.3.1
Summary: digSocialMediaIdExtractor
Home-page: https://github.com/usc-isi-i2/dig-socialmedia-id-extractor
Author: Rahul Kapoor
Author-email: rahulkap@isi.edu
License: UNKNOWN
Download-URL: https://github.com/usc-isi-i2/dig-socialmedia-id-extractor
Platform: UNKNOWN
